llamacalc/__init__.py
llamacalc/cache.py
llamacalc/cli.py
llamacalc/core.py
llamacalc/llamacalc.py
llamacalc/test_llamacalc.py
llamacalc_llamasearch-0.1.0.dist-info/licenses/LICENSE
llamacalc_llamasearch-0.1.0.dist-info/METADATA
llamacalc_llamasearch-0.1.0.dist-info/WHEEL
llamacalc_llamasearch-0.1.0.dist-info/entry_points.txt
llamacalc_llamasearch-0.1.0.dist-info/top_level.txt
llamacalc_llamasearch-0.1.0.dist-info/RECORD
