Metadata-Version: 2.4
Name: llamacalc-llamasearch
Version: 0.1.0
Summary: Advanced relevance scoring for LLM outputs
Home-page: https://llamasearch.ai
Author: LlamaSearch AI
Author-email: llamacalc-llamasearch <nikjois@llamasearch.ai>
License: MIT
Project-URL: Homepage, https://github.com/llamasearch/llamacalc
Project-URL: Bug Tracker, https://github.com/llamasearch/llamacalc/issues
Project-URL: Source, https://github.com/llamasearch/llamacalc
Keywords: llm,relevance,scoring,nlp,evaluation,mlx
Classifier: Development Status :: 4 - Beta
Classifier: Intended Audience :: Developers
Classifier: Intended Audience :: Science/Research
Classifier: License :: OSI Approved :: MIT License
Classifier: Programming Language :: Python :: 3
Classifier: Programming Language :: Python :: 3.8
Classifier: Programming Language :: Python :: 3.9
Classifier: Programming Language :: Python :: 3.10
Classifier: Programming Language :: Python :: 3.11
Classifier: Topic :: Scientific/Engineering :: Artificial Intelligence
Classifier: Topic :: Software Development :: Libraries :: Python Modules
Requires-Python: >=3.8
License-File: LICENSE
Requires-Dist: numpy>=1.20.0
Provides-Extra: ui
Requires-Dist: rich>=10.0.0; extra == "ui"
Provides-Extra: mlx
Requires-Dist: mlx>=0.0.5; extra == "mlx"
Provides-Extra: dev
Requires-Dist: pytest>=7.0.0; extra == "dev"
Requires-Dist: black>=23.0.0; extra == "dev"
Requires-Dist: isort>=5.12.0; extra == "dev"
Requires-Dist: mypy>=1.0.0; extra == "dev"
Requires-Dist: flake8>=6.0.0; extra == "dev"
Dynamic: author
Dynamic: home-page
Dynamic: license-file
Dynamic: requires-python
